{"kind":"controller","op_id":"c89dda600b077240e769dff8c21becb828ded1e2c0924abe91ce201865eef934","network":"testnet","target":"CARRZAC5H3N22SU6YCWITREOP6A4YSHIV7R7OKBNDO6KW4J3AIOHFNKZ","function":"create_liquidity_pool","args":[{"u32":1},{"address":"CCUUDM434BMZMYWYDITHFXHDMIVTGGD6T2I5UKNX5BSLXLW7HVR4MCGZ"},{"map":[{"key":{"symbol":"asset_decimals"},"val":{"u32":7}},{"key":{"symbol":"asset_id"},"val":{"address":"CCUUDM434BMZMYWYDITHFXHDMIVTGGD6T2I5UKNX5BSLXLW7HVR4MCGZ"}},{"key":{"symbol":"base_borrow_rate"},"val":{"i128":"10000000000000000000000000"}},{"key":{"symbol":"borrow_cap"},"val":{"i128":"100000000000000"}},{"key":{"symbol":"flashloan_fee"},"val":{"u32":9}},{"key":{"symbol":"is_flashloanable"},"val":{"bool":true}},{"key":{"symbol":"max_borrow_rate"},"val":{"i128":"2000000000000000000000000000"}},{"key":{"symbol":"max_utilization"},"val":{"i128":"950000000000000000000000000"}},{"key":{"symbol":"mid_utilization"},"val":{"i128":"500000000000000000000000000"}},{"key":{"symbol":"optimal_utilization"},"val":{"i128":"800000000000000000000000000"}},{"key":{"symbol":"reserve_factor"},"val":{"u32":1000}},{"key":{"symbol":"slope1"},"val":{"i128":"40000000000000000000000000"}},{"key":{"symbol":"slope2"},"val":{"i128":"100000000000000000000000000"}},{"key":{"symbol":"slope3"},"val":{"i128":"1500000000000000000000000000"}},{"key":{"symbol":"supply_cap"},"val":{"i128":"100000000000000"}}]}],"predecessor":"0000000000000000000000000000000000000000000000000000000000000000","salt":"be6e609bdf34fb93da44210af0bfe20e5d9c4eb807da97c508ae634bed6a3907","cli_executable":true}
